UzbekTagger/UzbekTagger.py
UzbekTagger/__init__.py
UzbekTagger/word.xml
uzbektagger-1.1.dist-info/licenses/LICENSE
uzbektagger-1.1.dist-info/METADATA
uzbektagger-1.1.dist-info/WHEEL
uzbektagger-1.1.dist-info/top_level.txt
uzbektagger-1.1.dist-info/RECORD
