Metadata-Version: 2.4
Name: UzbekTagger
Version: 1.1
Summary: Part of Speech Tagger for Uzbek Language.
Author-email: "Sharipov Maksud,Yuldashov Ollabergan" <maqsbek72@gmail.com>
Project-URL: Homepage, https://github.com/MaksudSharipov/UzbekTagger
Classifier: Programming Language :: Python :: 3
Classifier: License :: OSI Approved :: MIT License
Classifier: Operating System :: OS Independent
Requires-Python: >=3.7
License-File: LICENSE
Requires-Dist: nltk>=3.5
Dynamic: license-file
